MPGrid/MPGrid.cp311-win_amd64.pyd
MPGrid/__init__.py
MPGrid/include/MPGrid.h
MPGrid-0.0.5.dist-info/LICENSE
MPGrid-0.0.5.dist-info/METADATA
MPGrid-0.0.5.dist-info/WHEEL
MPGrid-0.0.5.dist-info/top_level.txt
MPGrid-0.0.5.dist-info/RECORD
