Metadata-Version: 2.1
Name: MPGrid
Version: 0.0.5
Summary: Python Library for Finite Difference Calculation
Author-email: Kenjiro Sugio <ksugio@hiroshima-u.ac.jp>
License: MIT License
Project-URL: Homepage, https://github.com/ksugio/MPGrid
Classifier: Development Status :: 4 - Beta
Classifier: Programming Language :: Python
Classifier: Programming Language :: Python :: 3
Requires-Python: >=3.8
License-File: LICENSE
Provides-Extra: dev
Requires-Dist: build ; extra == 'dev'
Requires-Dist: twine ; extra == 'dev'
